TorScrape/extensions.py
TorScrape/torscrape.py
torscraper-0.3.0.dist-info/licenses/LICENSE
torscraper-0.3.0.dist-info/METADATA
torscraper-0.3.0.dist-info/WHEEL
torscraper-0.3.0.dist-info/entry_points.txt
torscraper-0.3.0.dist-info/top_level.txt
torscraper-0.3.0.dist-info/RECORD
