Metadata-Version: 2.4
Name: TorScraper
Version: 0.3.0
Summary: Your dark web scraper using Tor
Author: DeadmanXXXII
Author-email: themadhattersplayground@gmail.com
Classifier: Programming Language :: Python :: 3
Classifier: License :: OSI Approved :: MIT License
Classifier: Operating System :: OS Independent
Requires-Python: >=3.10
License-File: LICENSE
Requires-Dist: selenium
Dynamic: author
Dynamic: author-email
Dynamic: classifier
Dynamic: license-file
Dynamic: requires-dist
Dynamic: requires-python
Dynamic: summary
